commons/__init__.py
commons/__version__.py
commons/databases/database.py
commons/databases/fs.py
commons/databases/gcs.py
commons/firebase_authentication/__init__.py
commons/firebase_authentication/authentication.py
commons/logger/__init__.py
commons/logger/dw_logger.py
commons/logger/logger.py
commons/pipeline_parameters/__init__.py
commons/pipeline_parameters/factory.py
commons/pipeline_parameters/parameter.py
commons/pipeline_parameters/validation.py
commons/schemas/internal_firestore.py
commons/schemas/pubsub_msg.py
commons/secrets/__init__.py
commons/secrets/secret_manager.py
commons/utils/__init__.py
commons/utils/constants.py
commons/utils/pubsub.py
commons/utils/time.py
dw_ai_x-0.0.57.dist-info/licenses/LICENSE
dw_ai_x-0.0.57.dist-info/METADATA
dw_ai_x-0.0.57.dist-info/WHEEL
dw_ai_x-0.0.57.dist-info/top_level.txt
dw_ai_x-0.0.57.dist-info/RECORD
