Metadata-Version: 2.4
Name: dw-ai-x
Version: 0.0.57
Summary: Common utilities shared with the community by Datwave AI Team
Author-email: Andrea Cola <andrea.cola@datwave.ai>
License-Expression: MIT
Requires-Python: <4.0,>=3.11
License-File: LICENSE
Requires-Dist: pydantic>=2.10.6
Requires-Dist: pydantic-settings>=2.6.1
Requires-Dist: google-cloud-storage>=2.18.2
Requires-Dist: google-cloud-bigquery>=3.27.0
Requires-Dist: google-cloud-bigquery-storage>=2.27.0
Requires-Dist: google-cloud-aiplatform>=1.73.0
Requires-Dist: google-cloud-logging>=3.11.3
Requires-Dist: google-cloud-secret-manager>=2.23.3
Requires-Dist: pandas>=2.2.3
Requires-Dist: joblib>=1.4.2
Requires-Dist: pytest>=8.3.4
Requires-Dist: aiofiles>=23.1.0
Requires-Dist: firebase-admin>=6.6.0
Requires-Dist: fastapi<0.118,>=0.115.7
Requires-Dist: google-cloud-alloydb-connector>=1.9.1
Requires-Dist: sqlalchemy>=2.0.43
Provides-Extra: test
Requires-Dist: pytest==8.3.4; extra == "test"
Dynamic: license-file
